Workbook

Sheet Readme_Index
A1: Projection Title | B1: Three-Statement Financial Modeling & DCF Valuation of Ethernal Ltd (Zomato/Blinkit)
A2: Author | B2: Aditya Kumar (BBA Graduate| Finance & Analytics)
A4: Sheet Index (Guide)
A5: 1. Readme_Index | B5: Project Overview, data sources, and sheet navigation guide
A6: 2. Historical Data | B6: 3- Year Annual P&L (FY24-FY26) and 4- Quarter historical results, Ratio Analysis and competitor comparison sourced from Screener. in
A7: 3. Assumptions | B7: Quarter-on-Quarter (QoQ) and Year-on-Year (YoY) revenue growth calculations.
A8: 4. Projections | B8: 5-Year conservative future forecasting (FY27 to FY31) using % of Revenue method.
A9: 5. DCF Valuation | B9: Intrinsic share price calculation using 11% WACC and 4% Perpetual Growth Rate.
A11: Key Insight: | B11: The model derives an intrinsic target share price of Rs. 250.17 based on 11% WACC and 4% growth rate, with sensitivity range of Rs. 199 to Rs. 418.

Sheet Historical Data
A1: Quarterly Particulars (Rs. Cr) | B1: 45809 | C1: 45901 | D1: 45992 | E1: 46082
A2: Sales | B2: 7167 | C2: 13590 | D2: 16315 | E2: 17292
A3: Expenses | B3: 7052 | C3: 13351 | D3: 15947 | E3: 16806
A4: Operating Profit | B4: 115 | C4: 239 | D4: 368 | E4: 486
A5: Net Profit | B5: 25 | C5: 65 | D5: 102 | E5: 174
A8: Annual Financials (Rs. Crores) | B8: 45352 | C8: 45717 | D8: 46082
A9: Annual Sales | B9: 12114 | C9: 20243 | D9: 54364
A10: Annual Expenses | B10: 12071 | C10: 19595 | D10: 53156
A11: Annual Operating Profit | B11: 43 | C11: 648 | D11: 1208

Sheet Assumptions
A1: Quarterly Metric | B1: Sep-2025 Growth % | C1: Dec-2025 Growth % | D1: Mar-2026 Growth %
A2: Sales Growth Rate (QoQ) | B2: =(('Historical Data'!C2-'Historical Data'!B2)/'Historical Data'!B2) -> 0.89619087 | C2: =(('Historical Data'!D2-'Historical Data'!C2)/'Historical Data'!C2) -> 0.20051508 | D2: =(('Historical Data'!E2-'Historical Data'!D2)/'Historical Data'!D2) -> 0.059883543
A4: Annual Metric | B4: FY-2025 Annual Growth % | C4: FY-2026 Annual Growth %
A5: Annual Sales Growth Rate | B5: =(('Historical Data'!C9-'Historical Data'!B9)/'Historical Data'!B9) -> 0.67104177 | C5: =(('Historical Data'!D9-'Historical Data'!C9)/'Historical Data'!C9) -> 1.6855703

Sheet Projections
A1: Particulars (Rs. Crores) | B1: Mar 2026 (A) | C1: Mar 2027 (E) | D1: Mar 2028 (E) | E1: Mar 2029 (E) | F1: Mar 2030 (E) | G1: Mar 2031 (E)
A2: Projected Sales | B2: ='Historical Data'!D9 -> 54364 | C2: =B2*(1+0.35) -> 73391.4 | D2: =C2*(1+0.3) -> 95408.82 | E2: =D2*(1+0.25) -> 119261.03 | F2: =E2*(1+0.2) -> 143113.23 | G2: =F2*(1+0.15) -> 164580.21
A3: Projected Expenses | B3: ='Historical Data'!D10 -> 53156 | C3: =C2*0.96 -> 70455.744 | D3: =D2*0.95 -> 90638.379 | E3: =E2*0.93 -> 110912.75 | F3: =F2*0.93 -> 133095.3 | G3: =G2*0.92 -> 151413.8
A4: Projected Operating Profit | B4: =B2-B3 -> 1208 | C4: =C2-C3 -> 2935.656 | D4: =D2-D3 -> 4770.441 | E4: =E2-E3 -> 8348.2717 | F4: =F2-F3 -> 10017.926 | G4: =G2-G3 -> 13166.417

Sheet DCF Valuation
A1: DCF Inputs
A2: WACC (Cost of Capital) | B2: 0.11
A3: Perpetual Growth Rate | B3: 0.04
A4: Enterprise Value Bridge
A5: FCFF Assumption (Assets-Light Proxy) | B5: CapEx ~1% of Revenue | C5: FCFF ≈ Operating Profit
A6: Year | B6: FY 2027 | C6: FY 2028 | D6: FY 2029 | E6: FY 2030 | F6: FY 2031
A7: Unlevered Free Cash Flow / FCFF (Proxy) | B7: =Projections!C4 -> 2935.656 | C7: =Projections!D4 -> 4770.441 | D7: =Projections!E4 -> 8348.2717 | E7: =Projections!F4 -> 10017.926 | F7: =Projections!G4 -> 13166.417
A8: Present Value (PV) Factor | B8: =1/((1+$B$2)^1) -> 0.9009009 | C8: =1/((1+$B$2)^2) -> 0.81162243 | D8: =1/((1+$B$2)^3) -> 0.73119138 | E8: =1/((1+$B$2)^4) -> 0.65873097 | F8: =1/((1+$B$2)^5) -> 0.59345133
A9: Discounted Cash Flow | B9: =B7*B8 -> 2644.7351 | C9: =C7*C8 -> 3871.7969 | D9: =D7*D8 -> 6104.1844 | E9: =E7*E8 -> 6599.1182 | F9: =F7*F8 -> 7813.6277
A11: Sum of PV of Cash Flows | B11: =SUM(B9:F9) -> 27033.462
A12: Terminal Value | B12: =(F7*(1+$B$3))/($B$2-$B$3) -> 195615.34
A13: Total Enterprise Value | B13: =B11+B12 -> 222648.8
A14: Total Shares Outstanding (Cr) | B14: 890
A15: Intrinsic Shares Price (Rs.) | B15: =B13/B14 -> 250.16719
A18: Sensitivity Analysis - Intrinsic Price (Rs.)
A19: WACC / Growth label | B19: 0.03 | C19: 0.04 | D19: 0.05
A20: 0.09 | B20: =((B11+(F7*(1+B19))/(A20-B19))/B14) -> 284.33366 | C20: =((B11+(F7*(1+C19))/(A20-C19))/B14) -> 338.0842 | D20: =((B11+(F7*(1+D19))/(A20-D19))/B14) -> 418.71001
A21: 0.1 | B21: =((B11+(F7*(1+B19))/(A21-B19))/B14) -> 248.0538 | C21: =((B11+(F7*(1+C19))/(A21-C19))/B14) -> 286.79928 | D21: =((B11+(F7*(1+D19))/(A21-D19))/B14) -> 341.04295
A22: 0.11 | B22: =((B11+(F7*(1+B19))/(A22-B19))/B14) -> 220.84391 | C22: =((B11+(F7*(1+C19))/(A22-C19))/B14) -> 250.16719 | D22: =((B11+(F7*(1+D19))/(A22-D19))/B14) -> 289.2649
A23: 0.12 | B23: =((B11+(F7*(1+B19))/(A23-B19))/B14) -> 199.68067 | C23: =((B11+(F7*(1+C19))/(A23-C19))/B14) -> 222.69313 | D23: =((B11+(F7*(1+D19))/(A23-D19))/B14) -> 252.28058

Sheet Ratio Analysis
A1: Metric | B1: FY-2026 (A) | C1: FY-2027 (E) | D1: FY-2028 (E) | E1: FY-2029 (E) | F1: FY-2030 (E) | G1: FY-2031 (E)
A2: Operating Margin % | B2: ='Historical Data'!E4/'Historical Data'!E2 -> 0.028105482 | C2: =Projections!C4/Projections!C2 -> 0.04 | D2: =Projections!D4/Projections!D2 -> 0.05 | E2: =Projections!E4/Projections!E2 -> 0.07 | F2: =Projections!F4/Projections!F2 -> 0.07 | G2: =Projections!G4/Projections!G2 -> 0.08
A3: Net Profit Margin % | B3: ='Historical Data'!E5/'Historical Data'!E2 -> 0.010062457 | C3: =Projections!C4/Projections!C2 -> 0.04 | D3: =Projections!D4/Projections!D2 -> 0.05 | E3: =Projections!E4/Projections!E2 -> 0.07 | F3: =Projections!F4/Projections!F2 -> 0.07 | G3: =Projections!G4/Projections!G2 -> 0.08
A4: Revenue Growth % | B4: =('Historical Data'!E2-'Historical Data'!D2)/'Historical Data'!D2 -> 0.059883543 | C4: =(Projections!C2-Projections!B2)/Projections!B2 -> 0.35 | D4: =(Projections!D2-Projections!C2)/Projections!C2 -> 0.3 | E4: =(Projections!E2-Projections!D2)/Projections!D2 -> 0.25 | F4: =(Projections!F2-Projections!E2)/Projections!E2 -> 0.2 | G4: =(Projections!G2-Projections!F2)/Projections!F2 -> 0.15
A6: Investment Recommendation | B6: BUY - Intrinsic Price Rs.250 vs Market Price Rs.230. Stock appears undervalued with 35% projected revenue growth.
A8: Competitor Comparison
A9: Company | B9: Revenue FY26 | C9: Operating Margin
A10: Zomato/Blinkit | B10: 54364 | C10: 0.03
A11: Swiggy | B11: ~12,000 | C11: ~2%
